odoo/addons/l10n_es_verifactu_oca/README.rst
odoo/addons/l10n_es_verifactu_oca/__init__.py
odoo/addons/l10n_es_verifactu_oca/__manifest__.py
odoo/addons/l10n_es_verifactu_oca/hooks.py
odoo/addons/l10n_es_verifactu_oca/data/account_fiscal_position_template_data.xml
odoo/addons/l10n_es_verifactu_oca/data/ir_config_parameter.xml
odoo/addons/l10n_es_verifactu_oca/data/ir_cron.xml
odoo/addons/l10n_es_verifactu_oca/data/mail_activity_data.xml
odoo/addons/l10n_es_verifactu_oca/data/neutralize.sql
odoo/addons/l10n_es_verifactu_oca/data/verifactu_map_data.xml
odoo/addons/l10n_es_verifactu_oca/data/verifactu_registration_key_data.xml
odoo/addons/l10n_es_verifactu_oca/data/verifactu_tax_agency_data.xml
odoo/addons/l10n_es_verifactu_oca/i18n/ca.po
odoo/addons/l10n_es_verifactu_oca/i18n/ca_ES.po
odoo/addons/l10n_es_verifactu_oca/i18n/es.po
odoo/addons/l10n_es_verifactu_oca/i18n/l10n_es_verifactu_oca.pot
odoo/addons/l10n_es_verifactu_oca/models/__init__.py
odoo/addons/l10n_es_verifactu_oca/models/account_fiscal_position.py
odoo/addons/l10n_es_verifactu_oca/models/account_fiscal_position_template.py
odoo/addons/l10n_es_verifactu_oca/models/account_journal.py
odoo/addons/l10n_es_verifactu_oca/models/account_move.py
odoo/addons/l10n_es_verifactu_oca/models/aeat_mixin.py
odoo/addons/l10n_es_verifactu_oca/models/aeat_tax_agency.py
odoo/addons/l10n_es_verifactu_oca/models/res_company.py
odoo/addons/l10n_es_verifactu_oca/models/res_partner.py
odoo/addons/l10n_es_verifactu_oca/models/verifactu_chaining.py
odoo/addons/l10n_es_verifactu_oca/models/verifactu_developer.py
odoo/addons/l10n_es_verifactu_oca/models/verifactu_invoice_entry.py
odoo/addons/l10n_es_verifactu_oca/models/verifactu_invoice_entry_response.py
odoo/addons/l10n_es_verifactu_oca/models/verifactu_invoice_entry_response_line.py
odoo/addons/l10n_es_verifactu_oca/models/verifactu_map.py
odoo/addons/l10n_es_verifactu_oca/models/verifactu_mixin.py
odoo/addons/l10n_es_verifactu_oca/models/verifactu_registration_key.py
odoo14_addon_l10n_es_verifactu_oca-14.0.1.0.3.dev2.dist-info/METADATA
odoo14_addon_l10n_es_verifactu_oca-14.0.1.0.3.dev2.dist-info/WHEEL
odoo14_addon_l10n_es_verifactu_oca-14.0.1.0.3.dev2.dist-info/top_level.txt
odoo14_addon_l10n_es_verifactu_oca-14.0.1.0.3.dev2.dist-info/RECORD
