Metadata-Version: 2.1
Name: odoo14-addon-l10n_es_verifactu_oca
Version: 14.0.1.0.3.dev2
Summary: Comunicación VERI*FACTU
Home-page: https://github.com/OCA/l10n-spain
Author: Aures Tic,ForgeFlow,Tecnativa,Odoo Community Association (OCA)
Author-email: support@odoo-community.org
License: AGPL-3
Classifier: Programming Language :: Python
Classifier: Framework :: Odoo
Classifier: Framework :: Odoo :: 14.0
Classifier: License :: OSI Approved :: GNU Affero General Public License v3
Requires-Python: >=3.6
Requires-Dist: odoo14-addon-account-invoice-refund-link
Requires-Dist: odoo14-addon-l10n-es-aeat
Requires-Dist: odoo<14.1dev,>=14.0a
